ask_sdk_dynamodb/__init__.py
ask_sdk_dynamodb/__version__.py
ask_sdk_dynamodb/adapter.py
ask_sdk_dynamodb/partition_keygen.py
ask_sdk_dynamodb/py.typed
ask_sdk_dynamodb_persistence_adapter-1.19.0.dist-info/METADATA
ask_sdk_dynamodb_persistence_adapter-1.19.0.dist-info/WHEEL
ask_sdk_dynamodb_persistence_adapter-1.19.0.dist-info/top_level.txt
ask_sdk_dynamodb_persistence_adapter-1.19.0.dist-info/RECORD
